swanlab/__init__.py
swanlab/env.py
swanlab/package.json
swanlab/cli/__init__.py
swanlab/cli/main.py
swanlab/cli/utils.py
swanlab/database/__init__.py
swanlab/database/chart.py
swanlab/database/expriment.py
swanlab/database/main.py
swanlab/database/project.py
swanlab/database/system.py
swanlab/database/table.py
swanlab/database/utils.py
swanlab/log/__init__.py
swanlab/log/console.py
swanlab/log/log.py
swanlab/server/__init__.py
swanlab/server/router.py
swanlab/server/web.py
swanlab/server/api/experiment.py
swanlab/server/api/project.py
swanlab/server/module/__init__.py
swanlab/server/module/resp.py
swanlab/server/module/models/experiment.py
swanlab/server/module/models/project.py
swanlab/server/module/models/tag.py
swanlab/template/index.html
swanlab/template/assets/404-g6bxZ6_v.js
swanlab/template/assets/ChartPage-3r0Q8xCu.css
swanlab/template/assets/ChartPage-bl4RMMgg.js
swanlab/template/assets/ExperimentView-3gJFPntg.js
swanlab/template/assets/ExperimentView-6mj1DMtw.css
swanlab/template/assets/HelpView-59mgVoSw.js
swanlab/template/assets/HomeView-Ka0fXhB8.css
swanlab/template/assets/HomeView-efgvWwjJ.js
swanlab/template/assets/IndexPage-tZrY54aQ.css
swanlab/template/assets/IndexPage-xn4QpS3n.js
swanlab/template/assets/JetBrainsMono-Regular-4d-ik58X.ttf
swanlab/template/assets/LogPage-9U9rUJKO.js
swanlab/template/assets/LogPage-mDO7Tan1.css
swanlab/template/assets/SLStatusLabel-8sEHEDvS.js
swanlab/template/assets/SLStatusLabel-p6ynrWUD.css
swanlab/template/assets/index-3EwLEbbQ.css
swanlab/template/assets/index-5Sx8wuLr.js
swanlab/template/assets/logo-oR39qM5B.ico
swanlab/utils/__init__.py
swanlab/utils/file.py
swanlab/utils/font.py
swanlab/utils/package.py
swanlab/utils/time.py
test_sw_12241-0.0.1.dist-info/METADATA
test_sw_12241-0.0.1.dist-info/WHEEL
test_sw_12241-0.0.1.dist-info/entry_points.txt
test_sw_12241-0.0.1.dist-info/licenses/LICENSE
test_sw_12241-0.0.1.dist-info/RECORD
