Metadata-Version: 2.1
Name: test-sw-12241
Version: 0.0.1
Summary: Python library for streamlined tracking and management of AI training processes.
Project-URL: Homepage, https://swabhub.co
Author-email: Cunyue <team@swanhub.co>, Feudalman <team@swanhub.co>, ZeYi Lin <team@swanhub.co>, KashiwaByte <team@swanhub.co>
License-Expression: Apache-2.0
License-File: LICENSE
Keywords: machine learning,reproducibility,visualization
Classifier: Development Status :: 3 - Alpha
Classifier: License :: OSI Approved :: Apache Software License
Classifier: Operating System :: OS Independent
Classifier: Programming Language :: Python :: 3
Classifier: Programming Language :: Python :: 3 :: Only
Classifier: Programming Language :: Python :: 3.8
Classifier: Programming Language :: Python :: 3.9
Classifier: Programming Language :: Python :: 3.10
Classifier: Programming Language :: Python :: 3.11
Classifier: Programming Language :: Python :: 3.12
Classifier: Topic :: Scientific/Engineering
Classifier: Topic :: Scientific/Engineering :: Artificial Intelligence
Classifier: Topic :: Scientific/Engineering :: Visualization
Requires-Python: >=3.8
Requires-Dist: click
Requires-Dist: fastapi
Requires-Dist: portalocker
Requires-Dist: psutil
Requires-Dist: ujson
Requires-Dist: uvicorn>=0.14.0
Provides-Extra: oauth
